hicat/__init__.py
hicat/hicat.py
hicat-1.1.6.dist-info/licenses/LICENSE
hicat-1.1.6.dist-info/METADATA
hicat-1.1.6.dist-info/WHEEL
hicat-1.1.6.dist-info/entry_points.txt
hicat-1.1.6.dist-info/top_level.txt
hicat-1.1.6.dist-info/RECORD
